{"v":4,"entries":{"example-alert--default":{"id":"example-alert--default","title":"Example/Alert","name":"Default","importPath":"./src/lib/atoms/alert/Alert.stories.svelte","tags":["story"],"type":"story"},"example-alert--info":{"id":"example-alert--info","title":"Example/Alert","name":"Info","importPath":"./src/lib/atoms/alert/Alert.stories.svelte","tags":["story"],"type":"story"},"example-alert--danger":{"id":"example-alert--danger","title":"Example/Alert","name":"Danger","importPath":"./src/lib/atoms/alert/Alert.stories.svelte","tags":["story"],"type":"story"}}}
